{
	"design__instance__displacement__total": 1042.53,
	"design__instance__displacement__mean": 0.42,
	"design__instance__displacement__max": 14.68,
	"route__wirelength__estimated": 62650.7,
	"design__violations": 0,
	"design__io": 128,
	"design__die__area": 90000,
	"design__core__area": 80146.9,
	"design__instance__count": 2275,
	"design__instance__area": 20063,
	"design__instance__count__stdcell": 2275,
	"design__instance__area__stdcell": 20063,
	"design__instance__count__macros": 0,
	"design__instance__area__macros": 0,
	"design__instance__utilization": 0.250328,
	"design__instance__utilization__stdcell": 0.250328,
	"flow__warnings__count": 33826,
	"flow__errors__count": 0
}